edfi_sql_adapter/__init__.py
edfi_sql_adapter/py.typed
edfi_sql_adapter/sql_adapter.py
edfi_sql_adapter-1.0.3.dist-info/METADATA
edfi_sql_adapter-1.0.3.dist-info/WHEEL
edfi_sql_adapter-1.0.3.dist-info/RECORD
