Metadata-Version: 2.1
Name: edfi-sql-adapter
Version: 1.0.3
Summary: Lightweight wrapper to facilitate connections to SQL databases
Home-page: https://docs.ed-fi.org/getting-started/edfi-exchange/technology/ed-fi-lms-toolkit
License: Apache-2.0
Author: Ed-Fi Alliance, LLC, and contributors
Requires-Python: >=3.9,<4.0
Classifier: License :: OSI Approved :: Apache Software License
Classifier: Programming Language :: Python :: 3
Classifier: Programming Language :: Python :: 3.9
Classifier: Programming Language :: Python :: 3.10
Classifier: Programming Language :: Python :: 3.11
Classifier: Programming Language :: Python :: 3.12
Requires-Dist: SQLAlchemy (>=1,<2)
Requires-Dist: psycopg2 (>=2.8.6,<3.0.0)
Requires-Dist: pyodbc (>=4.0.30,<5.0.0)
Project-URL: Repository, https://github.com/Ed-Fi-Exchange-OSS/LMS-Toolkit
